{
  "annotations": {
    "list": [
      {
        "builtIn": 1,
        "datasource": {
          "type": "grafana",
          "uid": "-- Grafana --"
        },
        "enable": true,
        "hide": true,
        "iconColor": "rgba(0, 211, 255, 1)",
        "name": "Annotations & Alerts",
        "type": "dashboard"
      }
    ]
  },
  "description": "ResMan v2.1 - SysAdmin Operations Dashboard. Shows system health, top consumers, limit effectiveness, CPU trends (instant/avg/EMA), IO throughput, and capacity planning. Designed for operational use.",
  "editable": true,
  "fiscalYearStartMonth": 0,
  "graphTooltip": 1,
  "links": [],
  "panels": [
    {
      "collapsed": false,
      "gridPos": {
        "h": 1,
        "w": 24,
        "x": 0,
        "y": 0
      },
      "id": 100,
      "panels": [],
      "title": "SYSTEM HEALTH AT A GLANCE",
      "type": "row"
    },
    {
      "datasource": {
        "type": "prometheus",
        "uid": "${prometheus_datasource}"
      },
      "fieldConfig": {
        "defaults": {
          "color": {
            "mode": "thresholds"
          },
          "mappings": [],
          "max": 100,
          "min": 0,
          "thresholds": {
            "mode": "absolute",
            "steps": [
              {
                "color": "green",
                "value": 0
              },
              {
                "color": "yellow",
                "value": 50
              },
              {
                "color": "red",
                "value": 75
              }
            ]
          },
          "unit": "percent"
        },
        "overrides": []
      },
      "gridPos": {
        "h": 4,
        "w": 4,
        "x": 0,
        "y": 1
      },
      "id": 1,
      "options": {
        "colorMode": "value",
        "graphMode": "area",
        "justifyMode": "auto",
        "orientation": "auto",
        "percentChangeColorMode": "standard",
        "reduceOptions": {
          "calcs": [
            "lastNotNull"
          ],
          "fields": "",
          "values": false
        },
        "showPercentChange": false,
        "textMode": "auto",
        "wideLayout": true
      },
      "pluginVersion": "12.4.2",
      "targets": [
        {
          "datasource": {
            "type": "prometheus",
            "uid": "${prometheus_datasource}"
          },
          "editorMode": "code",
          "expr": "resman_cpu_total_usage_percent{cluster=~\"$cluster\", server_role=~\"$server_role\", hostname=~\"$hostname\"}",
          "legendFormat": "{{hostname}}",
          "range": true,
          "refId": "A"
        }
      ],
      "title": "System CPU",
      "type": "stat"
    },
    {
      "datasource": {
        "type": "prometheus",
        "uid": "${prometheus_datasource}"
      },
      "fieldConfig": {
        "defaults": {
          "color": {
            "mode": "thresholds"
          },
          "mappings": [],
          "max": 100,
          "min": 0,
          "thresholds": {
            "mode": "absolute",
            "steps": [
              {
                "color": "green",
                "value": 0
              },
              {
                "color": "yellow",
                "value": 70
              },
              {
                "color": "red",
                "value": 85
              }
            ]
          },
          "unit": "percent"
        },
        "overrides": []
      },
      "gridPos": {
        "h": 4,
        "w": 4,
        "x": 4,
        "y": 1
      },
      "id": 2,
      "options": {
        "colorMode": "value",
        "graphMode": "area",
        "justifyMode": "auto",
        "orientation": "auto",
        "percentChangeColorMode": "standard",
        "reduceOptions": {
          "calcs": [
            "lastNotNull"
          ],
          "fields": "",
          "values": false
        },
        "showPercentChange": false,
        "textMode": "auto",
        "wideLayout": true
      },
      "pluginVersion": "12.4.2",
      "targets": [
        {
          "datasource": {
            "type": "prometheus",
            "uid": "${prometheus_datasource}"
          },
          "editorMode": "code",
          "expr": "(resman_memory_usage_megabytes{cluster=~\"$cluster\", server_role=~\"$server_role\", hostname=~\"$hostname\"} / resman_memory_total_megabytes{cluster=~\"$cluster\", server_role=~\"$server_role\", hostname=~\"$hostname\"}) * 100",
          "legendFormat": "{{hostname}}",
          "range": true,
          "refId": "A"
        }
      ],
      "title": "System Memory",
      "type": "stat"
    },
    {
      "datasource": {
        "type": "prometheus",
        "uid": "${prometheus_datasource}"
      },
      "fieldConfig": {
        "defaults": {
          "color": {
            "mode": "thresholds"
          },
          "mappings": [
            {
              "options": {
                "0": {
                  "color": "green",
                  "index": 0,
                  "text": "INACTIVE"
                }
              },
              "type": "value"
            },
            {
              "options": {
                "1": {
                  "color": "red",
                  "index": 1,
                  "text": "ACTIVE"
                }
              },
              "type": "value"
            }
          ],
          "thresholds": {
            "mode": "absolute",
            "steps": [
              {
                "color": "green",
                "value": 0
              },
              {
                "color": "red",
                "value": 1
              }
            ]
          }
        },
        "overrides": []
      },
      "gridPos": {
        "h": 4,
        "w": 4,
        "x": 8,
        "y": 1
      },
      "id": 3,
      "options": {
        "colorMode": "background",
        "graphMode": "none",
        "justifyMode": "auto",
        "orientation": "auto",
        "percentChangeColorMode": "standard",
        "reduceOptions": {
          "calcs": [
            "lastNotNull"
          ],
          "fields": "",
          "values": false
        },
        "showPercentChange": false,
        "textMode": "auto",
        "wideLayout": true
      },
      "pluginVersion": "12.4.2",
      "targets": [
        {
          "datasource": {
            "type": "prometheus",
            "uid": "${prometheus_datasource}"
          },
          "editorMode": "code",
          "expr": "resman_limits_active{cluster=~\"$cluster\", server_role=~\"$server_role\", hostname=~\"$hostname\"}",
          "legendFormat": "{{hostname}}",
          "range": true,
          "refId": "A"
        }
      ],
      "title": "Limits Status",
      "type": "stat"
    },
    {
      "datasource": {
        "type": "prometheus",
        "uid": "${prometheus_datasource}"
      },
      "fieldConfig": {
        "defaults": {
          "color": {
            "mode": "thresholds"
          },
          "mappings": [],
          "thresholds": {
            "mode": "absolute",
            "steps": [
              {
                "color": "green",
                "value": 0
              },
              {
                "color": "yellow",
                "value": 5
              },
              {
                "color": "red",
                "value": 10
              }
            ]
          }
        },
        "overrides": []
      },
      "gridPos": {
        "h": 4,
        "w": 4,
        "x": 12,
        "y": 1
      },
      "id": 4,
      "options": {
        "colorMode": "value",
        "graphMode": "none",
        "justifyMode": "auto",
        "orientation": "auto",
        "percentChangeColorMode": "standard",
        "reduceOptions": {
          "calcs": [
            "lastNotNull"
          ],
          "fields": "",
          "values": false
        },
        "showPercentChange": false,
        "textMode": "value_and_name",
        "wideLayout": true
      },
      "pluginVersion": "12.4.2",
      "targets": [
        {
          "datasource": {
            "type": "prometheus",
            "uid": "${prometheus_datasource}"
          },
          "expr": "resman_all_users_count{cluster=~\"$cluster\", server_role=~\"$server_role\", hostname=~\"$hostname\"}",
          "legendFormat": "Monitored",
          "refId": "A"
        },
        {
          "datasource": {
            "type": "prometheus",
            "uid": "${prometheus_datasource}"
          },
          "expr": "resman_limited_users_count_filtered{cluster=~\"$cluster\", server_role=~\"$server_role\", hostname=~\"$hostname\"}",
          "legendFormat": "Can Limit",
          "refId": "B"
        },
        {
          "datasource": {
            "type": "prometheus",
            "uid": "${prometheus_datasource}"
          },
          "expr": "resman_limited_users_count{cluster=~\"$cluster\", server_role=~\"$server_role\", hostname=~\"$hostname\"}",
          "legendFormat": "Currently Limited",
          "refId": "C"
        }
      ],
      "title": "Users",
      "type": "stat"
    },
    {
      "datasource": {
        "type": "prometheus",
        "uid": "${prometheus_datasource}"
      },
      "fieldConfig": {
        "defaults": {
          "color": {
            "mode": "thresholds"
          },
          "mappings": [],
          "thresholds": {
            "mode": "absolute",
            "steps": [
              {
                "color": "green",
                "value": 0
              },
              {
                "color": "yellow",
                "value": 2
              },
              {
                "color": "red",
                "value": 5
              }
            ]
          }
        },
        "overrides": []
      },
      "gridPos": {
        "h": 4,
        "w": 4,
        "x": 16,
        "y": 1
      },
      "id": 5,
      "options": {
        "colorMode": "value",
        "graphMode": "none",
        "justifyMode": "auto",
        "orientation": "auto",
        "percentChangeColorMode": "standard",
        "reduceOptions": {
          "calcs": [
            "lastNotNull"
          ],
          "fields": "",
          "values": false
        },
        "showPercentChange": false,
        "textMode": "auto",
        "wideLayout": true
      },
      "pluginVersion": "12.4.2",
      "targets": [
        {
          "datasource": {
            "type": "prometheus",
            "uid": "${prometheus_datasource}"
          },
          "editorMode": "code",
          "expr": "resman_system_load_average{cluster=~\"$cluster\", server_role=~\"$server_role\", hostname=~\"$hostname\"}",
          "legendFormat": "{{hostname}}",
          "range": true,
          "refId": "A"
        }
      ],
      "title": "Load Average",
      "type": "stat"
    },
    {
      "datasource": {
        "type": "prometheus",
        "uid": "${prometheus_datasource}"
      },
      "fieldConfig": {
        "defaults": {
          "color": {
            "mode": "thresholds"
          },
          "mappings": [],
          "thresholds": {
            "mode": "absolute",
            "steps": [
              {
                "color": "green",
                "value": 0
              },
              {
                "color": "yellow",
                "value": 10
              },
              {
                "color": "red",
                "value": 50
              }
            ]
          }
        },
        "overrides": []
      },
      "gridPos": {
        "h": 4,
        "w": 4,
        "x": 20,
        "y": 1
      },
      "id": 6,
      "options": {
        "colorMode": "value",
        "graphMode": "none",
        "justifyMode": "auto",
        "orientation": "auto",
        "percentChangeColorMode": "standard",
        "reduceOptions": {
          "calcs": [
            "lastNotNull"
          ],
          "fields": "",
          "values": false
        },
        "showPercentChange": false,
        "textMode": "auto",
        "wideLayout": true
      },
      "pluginVersion": "12.4.2",
      "targets": [
        {
          "datasource": {
            "type": "prometheus",
            "uid": "${prometheus_datasource}"
          },
          "editorMode": "code",
          "expr": "increase(resman_user_memory_high_breaches_total{cluster=~\"$cluster\", server_role=~\"$server_role\", hostname=~\"$hostname\"}[5m])",
          "legendFormat": "{{hostname}} (5m)",
          "range": true,
          "refId": "A"
        }
      ],
      "title": "Memory Warnings",
      "type": "stat"
    },
    {
      "collapsed": false,
      "gridPos": {
        "h": 1,
        "w": 24,
        "x": 0,
        "y": 5
      },
      "id": 200,
      "panels": [],
      "title": "TOP CONSUMERS - WHO IS USING RESOURCES RIGHT NOW",
      "type": "row"
    },
    {
      "datasource": {
        "type": "prometheus",
        "uid": "${prometheus_datasource}"
      },
      "fieldConfig": {
        "defaults": {
          "color": {
            "mode": "palette-classic"
          },
          "custom": {
            "axisBorderShow": false,
            "axisCenteredZero": false,
            "axisColorMode": "text",
            "axisLabel": "",
            "axisPlacement": "auto",
            "barAlignment": 0,
            "barWidthFactor": 0.6,
            "drawStyle": "line",
            "fillOpacity": 10,
            "gradientMode": "none",
            "hideFrom": {
              "legend": false,
              "tooltip": false,
              "viz": false
            },
            "insertNulls": false,
            "lineInterpolation": "linear",
            "lineWidth": 2,
            "pointSize": 5,
            "scaleDistribution": {
              "type": "linear"
            },
            "showPoints": "never",
            "showValues": false,
            "spanNulls": false,
            "stacking": {
              "group": "A",
              "mode": "none"
            },
            "thresholdsStyle": {
              "mode": "off"
            }
          },
          "mappings": [],
          "thresholds": {
            "mode": "absolute",
            "steps": [
              {
                "color": "green",
                "value": 0
              }
            ]
          },
          "unit": "percent"
        },
        "overrides": []
      },
      "gridPos": {
        "h": 8,
        "w": 12,
        "x": 0,
        "y": 6
      },
      "id": 7,
      "options": {
        "legend": {
          "calcs": [
            "max",
            "lastNotNull"
          ],
          "displayMode": "table",
          "placement": "bottom",
          "showLegend": true
        },
        "tooltip": {
          "hideZeros": false,
          "mode": "multi",
          "sort": "desc"
        }
      },
      "pluginVersion": "12.4.2",
      "targets": [
        {
          "datasource": {
            "type": "prometheus",
            "uid": "${prometheus_datasource}"
          },
          "editorMode": "code",
          "expr": "topk(5, resman_user_cpu_usage_percent{cluster=~\"$cluster\", server_role=~\"$server_role\", hostname=~\"$hostname\"})",
          "legendFormat": "{{username}}",
          "range": true,
          "refId": "A"
        }
      ],
      "title": "Top 5 Users by CPU (Instantaneous)",
      "type": "timeseries"
    },
    {
      "datasource": { "type": "prometheus", "uid": "${prometheus_datasource}" },
      "fieldConfig": {
        "defaults": {
          "color": { "mode": "palette-classic" },
          "custom": {
            "axisBorderShow": false,
            "axisCenteredZero": false,
            "axisColorMode": "text",
            "axisLabel": "",
            "axisPlacement": "auto",
            "barAlignment": 0,
            "barWidthFactor": 0.6,
            "drawStyle": "line",
            "fillOpacity": 0,
            "gradientMode": "none",
            "hideFrom": { "legend": false, "tooltip": false, "viz": false },
            "insertNulls": false,
            "lineInterpolation": "linear",
            "lineWidth": 2,
            "pointSize": 5,
            "scaleDistribution": { "type": "linear" },
            "showPoints": "never",
            "showValues": false,
            "spanNulls": false,
            "stacking": { "group": "A", "mode": "none" },
            "thresholdsStyle": { "mode": "off" }
          },
          "mappings": [],
          "thresholds": { "mode": "absolute", "steps": [{ "color": "green", "value": 0 }] },
          "unit": "percent"
        },
        "overrides": []
      },
      "gridPos": { "h": 8, "w": 12, "x": 12, "y": 6 },
      "id": 16,
      "options": {
        "legend": { "calcs": ["max", "mean"], "displayMode": "table", "placement": "bottom", "showLegend": true },
        "tooltip": { "hideZeros": false, "mode": "multi", "sort": "desc" }
      },
      "pluginVersion": "12.4.2",
      "targets": [
        {
          "datasource": { "type": "prometheus", "uid": "${prometheus_datasource}" },
          "expr": "topk(5, resman_user_cpu_usage_average_percent{cluster=~\"$cluster\", server_role=~\"$server_role\", hostname=~\"$hostname\"})",
          "legendFormat": "{{username}} (avg since start)",
          "range": true,
          "refId": "A"
        }
      ],
      "title": "Top 5 Users by CPU (Average Since Start)",
      "type": "timeseries"
    },
    {
      "datasource": {
        "type": "prometheus",
        "uid": "${prometheus_datasource}"
      },
      "fieldConfig": {
        "defaults": {
          "color": {
            "mode": "palette-classic"
          },
          "custom": {
            "axisBorderShow": false,
            "axisCenteredZero": false,
            "axisColorMode": "text",
            "axisLabel": "",
            "axisPlacement": "auto",
            "barAlignment": 0,
            "barWidthFactor": 0.6,
            "drawStyle": "line",
            "fillOpacity": 10,
            "gradientMode": "none",
            "hideFrom": {
              "legend": false,
              "tooltip": false,
              "viz": false
            },
            "insertNulls": false,
            "lineInterpolation": "linear",
            "lineWidth": 2,
            "pointSize": 5,
            "scaleDistribution": {
              "type": "linear"
            },
            "showPoints": "never",
            "showValues": false,
            "spanNulls": false,
            "stacking": {
              "group": "A",
              "mode": "none"
            },
            "thresholdsStyle": {
              "mode": "off"
            }
          },
          "mappings": [],
          "thresholds": {
            "mode": "absolute",
            "steps": [
              {
                "color": "green",
                "value": 0
              }
            ]
          },
          "unit": "bytes"
        },
        "overrides": []
      },
      "gridPos": {
        "h": 8,
        "w": 12,
        "x": 12,
        "y": 6
      },
      "id": 8,
      "options": {
        "legend": {
          "calcs": [
            "max",
            "lastNotNull"
          ],
          "displayMode": "table",
          "placement": "bottom",
          "showLegend": true
        },
        "tooltip": {
          "hideZeros": false,
          "mode": "multi",
          "sort": "desc"
        }
      },
      "pluginVersion": "12.4.2",
      "targets": [
        {
          "datasource": {
            "type": "prometheus",
            "uid": "${prometheus_datasource}"
          },
          "editorMode": "code",
          "expr": "topk(5, resman_user_memory_usage_bytes{cluster=~\"$cluster\", server_role=~\"$server_role\", hostname=~\"$hostname\"})",
          "legendFormat": "{{username}}",
          "range": true,
          "refId": "A"
        }
      ],
      "title": "Top 5 Users by Memory",
      "type": "timeseries"
    },
    {
      "collapsed": false,
      "gridPos": {
        "h": 1,
        "w": 24,
        "x": 0,
        "y": 14
      },
      "id": 300,
      "panels": [],
      "title": "LIMIT EFFECTIVENESS - ARE LIMITS WORKING",
      "type": "row"
    },
    {
      "datasource": {
        "type": "prometheus",
        "uid": "${prometheus_datasource}"
      },
      "fieldConfig": {
        "defaults": {
          "color": {
            "mode": "palette-classic"
          },
          "custom": {
            "axisBorderShow": false,
            "axisCenteredZero": false,
            "axisColorMode": "text",
            "axisLabel": "",
            "axisPlacement": "auto",
            "barAlignment": 0,
            "barWidthFactor": 0.6,
            "drawStyle": "line",
            "fillOpacity": 10,
            "gradientMode": "none",
            "hideFrom": {
              "legend": false,
              "tooltip": false,
              "viz": false
            },
            "insertNulls": false,
            "lineInterpolation": "linear",
            "lineWidth": 2,
            "pointSize": 5,
            "scaleDistribution": {
              "type": "linear"
            },
            "showPoints": "never",
            "showValues": false,
            "spanNulls": false,
            "stacking": {
              "group": "A",
              "mode": "none"
            },
            "thresholdsStyle": {
              "mode": "line"
            }
          },
          "mappings": [],
          "thresholds": {
            "mode": "absolute",
            "steps": [
              {
                "color": "green",
                "value": 0
              },
              {
                "color": "yellow",
                "value": 1
              },
              {
                "color": "red",
                "value": 10
              }
            ]
          },
          "unit": "short"
        },
        "overrides": []
      },
      "gridPos": {
        "h": 8,
        "w": 12,
        "x": 0,
        "y": 15
      },
      "id": 9,
      "options": {
        "legend": {
          "calcs": [
            "max",
            "lastNotNull"
          ],
          "displayMode": "table",
          "placement": "bottom",
          "showLegend": true
        },
        "tooltip": {
          "hideZeros": false,
          "mode": "multi",
          "sort": "desc"
        }
      },
      "pluginVersion": "12.4.2",
      "targets": [
        {
          "datasource": {
            "type": "prometheus",
            "uid": "${prometheus_datasource}"
          },
          "expr": "increase(resman_user_memory_high_breaches_total{cluster=~\"$cluster\", server_role=~\"$server_role\", hostname=~\"$hostname\"}[15m])",
          "legendFormat": "{{username}} - High Breaches",
          "refId": "A"
        }
      ],
      "title": "Memory High Breaches (Last 15m) - Users at Risk of OOM",
      "type": "timeseries"
    },
    {
      "datasource": {
        "type": "prometheus",
        "uid": "${prometheus_datasource}"
      },
      "fieldConfig": {
        "defaults": {
          "color": {
            "mode": "palette-classic"
          },
          "custom": {
            "axisBorderShow": false,
            "axisCenteredZero": false,
            "axisColorMode": "text",
            "axisLabel": "",
            "axisPlacement": "auto",
            "barAlignment": 0,
            "barWidthFactor": 0.6,
            "drawStyle": "line",
            "fillOpacity": 10,
            "gradientMode": "none",
            "hideFrom": {
              "legend": false,
              "tooltip": false,
              "viz": false
            },
            "insertNulls": false,
            "lineInterpolation": "linear",
            "lineWidth": 2,
            "pointSize": 5,
            "scaleDistribution": {
              "type": "linear"
            },
            "showPoints": "never",
            "showValues": false,
            "spanNulls": false,
            "stacking": {
              "group": "A",
              "mode": "none"
            },
            "thresholdsStyle": {
              "mode": "off"
            }
          },
          "mappings": [],
          "thresholds": {
            "mode": "absolute",
            "steps": [
              {
                "color": "green",
                "value": 0
              }
            ]
          }
        },
        "overrides": []
      },
      "gridPos": {
        "h": 8,
        "w": 12,
        "x": 12,
        "y": 15
      },
      "id": 10,
      "options": {
        "legend": {
          "calcs": [],
          "displayMode": "list",
          "placement": "bottom",
          "showLegend": true
        },
        "tooltip": {
          "hideZeros": false,
          "mode": "multi",
          "sort": "none"
        }
      },
      "pluginVersion": "12.4.2",
      "targets": [
        {
          "datasource": {
            "type": "prometheus",
            "uid": "${prometheus_datasource}"
          },
          "expr": "rate(resman_limits_activated_total{cluster=~\"$cluster\", server_role=~\"$server_role\", hostname=~\"$hostname\"}[5m]) * 300",
          "legendFormat": "Activations per 5m",
          "refId": "A"
        },
        {
          "datasource": {
            "type": "prometheus",
            "uid": "${prometheus_datasource}"
          },
          "expr": "rate(resman_limits_deactivated_total{cluster=~\"$cluster\", server_role=~\"$server_role\", hostname=~\"$hostname\"}[5m]) * 300",
          "legendFormat": "Deactivations per 5m",
          "refId": "B"
        }
      ],
      "title": "Limit Activation Frequency (per 5m window)",
      "type": "timeseries"
    },
    {
      "collapsed": false,
      "gridPos": {
        "h": 1,
        "w": 24,
        "x": 0,
        "y": 23
      },
      "id": 400,
      "panels": [],
      "title": "CAPACITY TRENDS - ARE WE RUNNING OUT OF HEADROOM",
      "type": "row"
    },
    {
      "datasource": {
        "type": "prometheus",
        "uid": "${prometheus_datasource}"
      },
      "fieldConfig": {
        "defaults": {
          "color": {
            "mode": "palette-classic"
          },
          "custom": {
            "axisBorderShow": false,
            "axisCenteredZero": false,
            "axisColorMode": "text",
            "axisLabel": "",
            "axisPlacement": "auto",
            "barAlignment": 0,
            "barWidthFactor": 0.6,
            "drawStyle": "line",
            "fillOpacity": 10,
            "gradientMode": "none",
            "hideFrom": {
              "legend": false,
              "tooltip": false,
              "viz": false
            },
            "insertNulls": false,
            "lineInterpolation": "linear",
            "lineWidth": 2,
            "pointSize": 5,
            "scaleDistribution": {
              "type": "linear"
            },
            "showPoints": "never",
            "showValues": false,
            "spanNulls": false,
            "stacking": {
              "group": "A",
              "mode": "none"
            },
            "thresholdsStyle": {
              "mode": "line+area"
            }
          },
          "mappings": [],
          "thresholds": {
            "mode": "absolute",
            "steps": [
              {
                "color": "green",
                "value": 0
              },
              {
                "color": "yellow",
                "value": 60
              },
              {
                "color": "red",
                "value": 80
              }
            ]
          },
          "unit": "percent"
        },
        "overrides": []
      },
      "gridPos": {
        "h": 8,
        "w": 12,
        "x": 0,
        "y": 24
      },
      "id": 11,
      "options": {
        "legend": {
          "calcs": [
            "mean",
            "max"
          ],
          "displayMode": "table",
          "placement": "bottom",
          "showLegend": true
        },
        "tooltip": {
          "hideZeros": false,
          "mode": "multi",
          "sort": "desc"
        }
      },
      "pluginVersion": "12.4.2",
      "targets": [
        {
          "datasource": {
            "type": "prometheus",
            "uid": "${prometheus_datasource}"
          },
          "expr": "resman_all_users_cpu_usage_percent{cluster=~\"$cluster\", server_role=~\"$server_role\", hostname=~\"$hostname\"}",
          "legendFormat": "All Users CPU",
          "refId": "A"
        },
        {
          "datasource": {
            "type": "prometheus",
            "uid": "${prometheus_datasource}"
          },
          "expr": "resman_cpu_total_usage_percent{cluster=~\"$cluster\", server_role=~\"$server_role\", hostname=~\"$hostname\"}",
          "legendFormat": "Total System CPU",
          "refId": "B"
        }
      ],
      "title": "System vs Users CPU Trend",
      "type": "timeseries"
    },
    {
      "datasource": { "type": "prometheus", "uid": "${prometheus_datasource}" },
      "fieldConfig": {
        "defaults": {
          "color": { "mode": "palette-classic" },
          "custom": {
            "axisBorderShow": false,
            "axisCenteredZero": false,
            "axisColorMode": "text",
            "axisLabel": "",
            "axisPlacement": "auto",
            "barAlignment": 0,
            "barWidthFactor": 0.6,
            "drawStyle": "line",
            "fillOpacity": 0,
            "gradientMode": "none",
            "hideFrom": { "legend": false, "tooltip": false, "viz": false },
            "insertNulls": false,
            "lineInterpolation": "linear",
            "lineWidth": 2,
            "pointSize": 5,
            "scaleDistribution": { "type": "linear" },
            "showPoints": "never",
            "showValues": false,
            "spanNulls": false,
            "stacking": { "group": "A", "mode": "none" },
            "thresholdsStyle": { "mode": "off" }
          },
          "mappings": [],
          "thresholds": { "mode": "absolute", "steps": [{ "color": "green", "value": 0 }] },
          "unit": "percent"
        },
        "overrides": [
          { "matcher": { "id": "byRegexp", "options": ".*Instantaneous.*" }, "properties": [{ "id": "lineWidth", "value": 3 }] },
          { "matcher": { "id": "byRegexp", "options": ".*Average.*" }, "properties": [{ "id": "lineWidth", "value": 2 }, { "id": "custom.lineStyle", "value": { "dash": [5, 5], "fill": "dash" } }] },
          { "matcher": { "id": "byRegexp", "options": ".*EMA.*" }, "properties": [{ "id": "lineWidth", "value": 2 }, { "id": "color", "value": { "fixedColor": "orange", "mode": "fixed" } }] }
        ]
      },
      "gridPos": { "h": 8, "w": 12, "x": 12, "y": 24 },
      "id": 17,
      "options": {
        "legend": { "calcs": ["mean", "max", "lastNotNull"], "displayMode": "table", "placement": "bottom", "showLegend": true },
        "tooltip": { "hideZeros": false, "mode": "multi", "sort": "desc" }
      },
      "pluginVersion": "12.4.2",
      "targets": [
        {
          "datasource": { "type": "prometheus", "uid": "${prometheus_datasource}" },
          "expr": "topk(3, resman_user_cpu_usage_percent{cluster=~\"$cluster\", server_role=~\"$server_role\", hostname=~\"$hostname\"})",
          "legendFormat": "{{username}} (Instantaneous)",
          "range": true,
          "refId": "A"
        },
        {
          "datasource": { "type": "prometheus", "uid": "${prometheus_datasource}" },
          "expr": "topk(3, resman_user_cpu_usage_average_percent{cluster=~\"$cluster\", server_role=~\"$server_role\", hostname=~\"$hostname\"})",
          "legendFormat": "{{username}} (Average)",
          "range": true,
          "refId": "B"
        },
        {
          "datasource": { "type": "prometheus", "uid": "${prometheus_datasource}" },
          "expr": "topk(3, resman_user_cpu_usage_ema_percent{cluster=~\"$cluster\", server_role=~\"$server_role\", hostname=~\"$hostname\"})",
          "legendFormat": "{{username}} (EMA)",
          "range": true,
          "refId": "C"
        }
      ],
      "title": "CPU Comparison: Instant vs Average vs EMA (Top 3)",
      "type": "timeseries"
    },
    {
      "datasource": {
        "type": "prometheus",
        "uid": "${prometheus_datasource}"
      },
      "fieldConfig": {
        "defaults": {
          "color": {
            "mode": "palette-classic"
          },
          "custom": {
            "axisBorderShow": false,
            "axisCenteredZero": false,
            "axisColorMode": "text",
            "axisLabel": "",
            "axisPlacement": "auto",
            "barAlignment": 0,
            "barWidthFactor": 0.6,
            "drawStyle": "line",
            "fillOpacity": 10,
            "gradientMode": "none",
            "hideFrom": {
              "legend": false,
              "tooltip": false,
              "viz": false
            },
            "insertNulls": false,
            "lineInterpolation": "linear",
            "lineWidth": 2,
            "pointSize": 5,
            "scaleDistribution": {
              "type": "linear"
            },
            "showPoints": "never",
            "showValues": false,
            "spanNulls": false,
            "stacking": {
              "group": "A",
              "mode": "none"
            },
            "thresholdsStyle": {
              "mode": "off"
            }
          },
          "mappings": [],
          "thresholds": {
            "mode": "absolute",
            "steps": [
              {
                "color": "green",
                "value": 0
              }
            ]
          },
          "unit": "short"
        },
        "overrides": []
      },
      "gridPos": {
        "h": 8,
        "w": 12,
        "x": 12,
        "y": 24
      },
      "id": 12,
      "options": {
        "legend": {
          "calcs": [
            "mean",
            "max"
          ],
          "displayMode": "table",
          "placement": "bottom",
          "showLegend": true
        },
        "tooltip": {
          "hideZeros": false,
          "mode": "multi",
          "sort": "desc"
        }
      },
      "pluginVersion": "12.4.2",
      "targets": [
        {
          "datasource": {
            "type": "prometheus",
            "uid": "${prometheus_datasource}"
          },
          "expr": "resman_all_users_count{cluster=~\"$cluster\", server_role=~\"$server_role\", hostname=~\"$hostname\"}",
          "legendFormat": "Total Users",
          "refId": "A"
        },
        {
          "datasource": {
            "type": "prometheus",
            "uid": "${prometheus_datasource}"
          },
          "expr": "resman_limited_users_count{cluster=~\"$cluster\", server_role=~\"$server_role\", hostname=~\"$hostname\"}",
          "legendFormat": "Limited Users",
          "refId": "B"
        }
      ],
      "title": "Active Users Trend",
      "type": "timeseries"
    },
    {
      "collapsed": false,
      "gridPos": {
        "h": 1,
        "w": 24,
        "x": 0,
        "y": 32
      },
      "id": 500,
      "panels": [],
      "title": "IO PERFORMANCE - DISK THROUGHPUT AND LATENCY",
      "type": "row"
    },
    {
      "datasource": {
        "type": "prometheus",
        "uid": "${prometheus_datasource}"
      },
      "fieldConfig": {
        "defaults": {
          "color": {
            "mode": "palette-classic"
          },
          "custom": {
            "axisBorderShow": false,
            "axisCenteredZero": false,
            "axisColorMode": "text",
            "axisLabel": "",
            "axisPlacement": "auto",
            "barAlignment": 0,
            "barWidthFactor": 0.6,
            "drawStyle": "line",
            "fillOpacity": 10,
            "gradientMode": "none",
            "hideFrom": {
              "legend": false,
              "tooltip": false,
              "viz": false
            },
            "insertNulls": false,
            "lineInterpolation": "linear",
            "lineWidth": 2,
            "pointSize": 5,
            "scaleDistribution": {
              "type": "linear"
            },
            "showPoints": "never",
            "showValues": false,
            "spanNulls": false,
            "stacking": {
              "group": "A",
              "mode": "none"
            },
            "thresholdsStyle": {
              "mode": "off"
            }
          },
          "mappings": [],
          "thresholds": {
            "mode": "absolute",
            "steps": [
              {
                "color": "green",
                "value": 0
              }
            ]
          },
          "unit": "Bps"
        },
        "overrides": []
      },
      "gridPos": {
        "h": 8,
        "w": 12,
        "x": 0,
        "y": 33
      },
      "id": 13,
      "options": {
        "legend": {
          "calcs": [
            "max",
            "mean"
          ],
          "displayMode": "table",
          "placement": "bottom",
          "showLegend": true
        },
        "tooltip": {
          "hideZeros": false,
          "mode": "multi",
          "sort": "desc"
        }
      },
      "pluginVersion": "12.4.2",
      "targets": [
        {
          "datasource": {
            "type": "prometheus",
            "uid": "${prometheus_datasource}"
          },
          "expr": "topk(5, rate(resman_user_io_read_bytes_total{cluster=~\"$cluster\", server_role=~\"$server_role\", hostname=~\"$hostname\"}[5m]))",
          "legendFormat": "{{username}} - Read",
          "refId": "A"
        },
        {
          "datasource": {
            "type": "prometheus",
            "uid": "${prometheus_datasource}"
          },
          "expr": "topk(5, rate(resman_user_io_write_bytes_total{cluster=~\"$cluster\", server_role=~\"$server_role\", hostname=~\"$hostname\"}[5m]))",
          "legendFormat": "{{username}} - Write",
          "refId": "B"
        }
      ],
      "title": "Top 5 Users by IO Throughput (5m rate)",
      "type": "timeseries"
    },
    {
      "datasource": {
        "type": "prometheus",
        "uid": "${prometheus_datasource}"
      },
      "fieldConfig": {
        "defaults": {
          "color": {
            "mode": "palette-classic"
          },
          "custom": {
            "axisBorderShow": false,
            "axisCenteredZero": false,
            "axisColorMode": "text",
            "axisLabel": "",
            "axisPlacement": "auto",
            "barAlignment": 0,
            "barWidthFactor": 0.6,
            "drawStyle": "line",
            "fillOpacity": 10,
            "gradientMode": "none",
            "hideFrom": {
              "legend": false,
              "tooltip": false,
              "viz": false
            },
            "insertNulls": false,
            "lineInterpolation": "linear",
            "lineWidth": 2,
            "pointSize": 5,
            "scaleDistribution": {
              "type": "linear"
            },
            "showPoints": "never",
            "showValues": false,
            "spanNulls": false,
            "stacking": {
              "group": "A",
              "mode": "none"
            },
            "thresholdsStyle": {
              "mode": "off"
            }
          },
          "mappings": [],
          "thresholds": {
            "mode": "absolute",
            "steps": [
              {
                "color": "green",
                "value": 0
              }
            ]
          },
          "unit": "ops"
        },
        "overrides": []
      },
      "gridPos": {
        "h": 8,
        "w": 12,
        "x": 12,
        "y": 33
      },
      "id": 14,
      "options": {
        "legend": {
          "calcs": [
            "max",
            "mean"
          ],
          "displayMode": "table",
          "placement": "bottom",
          "showLegend": true
        },
        "tooltip": {
          "hideZeros": false,
          "mode": "multi",
          "sort": "desc"
        }
      },
      "pluginVersion": "12.4.2",
      "targets": [
        {
          "datasource": {
            "type": "prometheus",
            "uid": "${prometheus_datasource}"
          },
          "expr": "topk(5, rate(resman_user_io_read_ops_total{cluster=~\"$cluster\", server_role=~\"$server_role\", hostname=~\"$hostname\"}[5m]))",
          "legendFormat": "{{username}} - Read Ops",
          "refId": "A"
        },
        {
          "datasource": {
            "type": "prometheus",
            "uid": "${prometheus_datasource}"
          },
          "expr": "topk(5, rate(resman_user_io_write_ops_total{cluster=~\"$cluster\", server_role=~\"$server_role\", hostname=~\"$hostname\"}[5m]))",
          "legendFormat": "{{username}} - Write Ops",
          "refId": "B"
        }
      ],
      "title": "Top 5 Users by IO Operations (5m rate)",
      "type": "timeseries"
    },
    {
      "datasource": {
        "type": "prometheus",
        "uid": "${prometheus_datasource}"
      },
      "fieldConfig": {
        "defaults": {
          "color": {
            "mode": "palette-classic"
          },
          "custom": {
            "axisBorderShow": false,
            "axisCenteredZero": false,
            "axisColorMode": "text",
            "axisLabel": "",
            "axisPlacement": "auto",
            "barAlignment": 0,
            "barWidthFactor": 0.6,
            "drawStyle": "line",
            "fillOpacity": 10,
            "gradientMode": "none",
            "hideFrom": {
              "legend": false,
              "tooltip": false,
              "viz": false
            },
            "insertNulls": false,
            "lineInterpolation": "linear",
            "lineWidth": 2,
            "pointSize": 5,
            "scaleDistribution": {
              "type": "linear"
            },
            "showPoints": "never",
            "showValues": false,
            "spanNulls": false,
            "stacking": {
              "group": "A",
              "mode": "none"
            },
            "thresholdsStyle": {
              "mode": "off"
            }
          },
          "mappings": [],
          "thresholds": {
            "mode": "absolute",
            "steps": [
              {
                "color": "green",
                "value": 0
              }
            ]
          },
          "unit": "Bps"
        },
        "overrides": []
      },
      "gridPos": {
        "h": 8,
        "w": 24,
        "x": 0,
        "y": 41
      },
      "id": 15,
      "options": {
        "legend": {
          "calcs": [
            "max",
            "mean",
            "sum"
          ],
          "displayMode": "table",
          "placement": "bottom",
          "showLegend": true
        },
        "tooltip": {
          "hideZeros": false,
          "mode": "multi",
          "sort": "desc"
        }
      },
      "pluginVersion": "12.4.2",
      "targets": [
        {
          "datasource": {
            "type": "prometheus",
            "uid": "${prometheus_datasource}"
          },
          "expr": "sum(rate(resman_user_io_read_bytes_total{cluster=~\"$cluster\", server_role=~\"$server_role\", hostname=~\"$hostname\"}[5m]))",
          "legendFormat": "Total Read",
          "refId": "A"
        },
        {
          "datasource": {
            "type": "prometheus",
            "uid": "${prometheus_datasource}"
          },
          "editorMode": "code",
          "expr": "sum(rate(resman_user_io_write_bytes_total{cluster=~\"$cluster\", server_role=~\"$server_role\", hostname=~\"$hostname\"}[5m]))",
          "legendFormat": "{{hostname}}",
          "range": true,
          "refId": "B"
        }
      ],
      "title": "Total System IO Throughput (All Users)",
      "type": "timeseries"
    }
  ],
  "preload": false,
  "refresh": "",
  "schemaVersion": 42,
  "tags": [
    "resman",
    "sysadmin",
    "operations"
  ],
  "templating": {
    "list": [
      {
        "current": {
          "text": "default",
          "value": "default"
        },
        "includeAll": false,
        "label": "Prometheus",
        "name": "prometheus_datasource",
        "options": [],
        "query": "prometheus",
        "refresh": 1,
        "regex": "",
        "type": "datasource"
      },
      {
        "allValue": ".*",
        "current": {
          "text": "All",
          "value": "$__all"
        },
        "datasource": {
          "type": "prometheus",
          "uid": "${prometheus_datasource}"
        },
        "definition": "label_values(resman_cpu_total_usage_percent, cluster)",
        "includeAll": true,
        "label": "Cluster",
        "multi": true,
        "name": "cluster",
        "options": [],
        "query": {
          "query": "label_values(resman_cpu_total_usage_percent, cluster)",
          "refId": "StandardVariableQuery"
        },
        "refresh": 1,
        "regex": "",
        "regexApplyTo": "value",
        "type": "query"
      },
      {
        "allValue": ".*",
        "current": {
          "text": "All",
          "value": "$__all"
        },
        "datasource": {
          "type": "prometheus",
          "uid": "${prometheus_datasource}"
        },
        "definition": "label_values(resman_cpu_total_usage_percent{cluster=~\"$cluster\"}, server_role)",
        "includeAll": true,
        "label": "Server Role",
        "multi": true,
        "name": "server_role",
        "options": [],
        "query": {
          "query": "label_values(resman_cpu_total_usage_percent{cluster=~\"$cluster\"}, server_role)",
          "refId": "StandardVariableQuery"
        },
        "refresh": 1,
        "regex": "",
        "regexApplyTo": "value",
        "type": "query"
      },
      {
        "allValue": ".*",
        "current": {
          "text": "All",
          "value": "$__all"
        },
        "datasource": {
          "type": "prometheus",
          "uid": "${prometheus_datasource}"
        },
        "definition": "label_values(resman_cpu_total_usage_percent{cluster=~\"$cluster\", server_role=~\"$server_role\"}, hostname)",
        "includeAll": true,
        "label": "Hostname",
        "multi": true,
        "name": "hostname",
        "options": [],
        "query": {
          "query": "label_values(resman_cpu_total_usage_percent{cluster=~\"$cluster\", server_role=~\"$server_role\"}, hostname)",
          "refId": "StandardVariableQuery"
        },
        "refresh": 1,
        "regex": "",
        "regexApplyTo": "value",
        "type": "query"
      }
    ]
  },
  "time": {
    "from": "now-15m",
    "to": "now"
  },
  "timepicker": {},
  "timezone": "browser",
  "title": "ResMan v2.1 - SysAdmin Operations Dashboard",
  "uid": "resman-sysadmin-v2",
  "version": 10,
  "weekStart": ""
}
